SVAssertions_FIFO/TestBench/design.sv
// Code your design here

module FIFO(input clk, rst, wr, rd, 
            input [7:0] din,output reg [7:0] dout,
            output reg empty, full);
  
  reg [3:0] wptr = 0,rptr = 0,cnt = 0;
  reg [7:0] mem [15:0];
  
 
  always@(posedge clk)
    begin
      if(rst== 1'b1)
         begin
           cnt <= 0;
           wptr <= 0;
           rptr <= 0;
         end
      else if(wr && !full)
          begin
            if(cnt < 15) begin
            mem[wptr] <= din;
            wptr <= wptr + 1;
            cnt <= cnt + 1;
            end
          end
      else if (rd && !empty)
        begin
          if(cnt > 0) begin
          dout <= mem[rptr];
          rptr <= rptr + 1;
          cnt <= cnt - 1;
          end
        end 
      
      if(wptr == 15)
         wptr <= 0;
      if(rptr == 15)
         rptr <= 0;
    end
  
  assign empty = (cnt == 0) ? 1'b1 : 1'b0;
  assign full = (cnt == 15) ? 1'b1 : 1'b0;
  
endmodule

interface fifo_if;
  
  logic clock, rd, wr;         // Clock, read, and write signals
  logic full, empty;           // Flags indicating FIFO status
  logic [7:0] data_in;         // Data input
  logic [7:0] data_out;        // Data output
  logic rst;                   // Reset signal
 
endinterface

SVAssertions_FIFO/Assertion/testbench.sv
// Code your testbench here
// or browse Examples
module assert_fifo (input clk, rst, wr, rd, 
                    input [7:0] din,input [7:0] dout,
            input empty, full);
  
  
  // (1) status of full and empty when rst asserted
  
  ////check on edge
  
 RST_1: assert property (@(posedge clk) $rose(rst) |-> (full == 1'b0 && empty == 1'b1))$info("A1 Suc at %0t",$time);
   
  /////check on level
   
 RST_2: assert property (@(posedge clk) rst |-> (full == 1'b0 && empty == 1'b1))$info("A2 Suc at %0t",$time);  
 
  
   //  (2) operation of full and empty flag
     
   FULL_1: assert property (@(posedge clk) disable iff(rst) $rose(full) |=> (FIFO.wptr == 0)[*1:$] ##1 !full)$info("full Suc at %0t",$time); 
   
   FULL_2 : assert property (@(posedge clk) disable iff(rst) (FIFO.cnt == 15) |-> full)$info("full Suc at %0t",$time);
     
       
   EMPTY_1:  assert property (@(posedge clk) disable iff(rst) $rose(empty) |=> (FIFO.rptr == 0)[*1:$] ##1 !empty)$info("full Suc at %0t",$time); 
       
  
  EMPTY_2: assert property (@(posedge clk) disable iff(rst) (FIFO.cnt == 0) |-> empty)$info("empty Suc at %0t",$time); 
     
       
       
   ///////  (3) read while empty
  
    READ_EMPTY: assert property (@(posedge clk) disable iff(rst) empty |-> !rd)$info("Suc at %0t",$time);  
 
      ////////// (4) Write while FULL
     
    WRITE_FULL: assert property (@(posedge clk) disable iff(rst) full |-> !wr)$info("Suc at %0t",$time);
  
      
      ////////////// (5) Write+Read pointer behavior with rd and wr signal
 
      
      //////if wr high and full is low, wptr must incr
       
  WPTR1: assert property (@(posedge clk)  !rst && wr && !full |=> $changed(FIFO.wptr));
         
    //////// if wr is low, wptr must constant
  WPTR2: assert property (@(posedge clk) !rst && !wr |=> $stable(FIFO.wptr));
    
    /////// if rd is high, wptr must stay constant
  WPTR3: assert property (@(posedge clk)  !rst && rd |=> $stable(FIFO.wptr)) ;
         
   
  RPTR1: assert property (@(posedge clk)  !rst && rd && !empty |=> $changed(FIFO.rptr));
         
  RPTR2: assert property (@(posedge clk) !rst && !rd |=> $stable(FIFO.rptr));
    
  RPTR3: assert property (@(posedge clk)  !rst && wr |=> $stable(FIFO.rptr));
 
  
      
    
    //////////  (6) state of all the i/o ports for all clock edge
  
  
  
 
 
  always@(posedge clk)
    begin
      assert (!$isunknown(dout));
      assert (!$isunknown(rst));
      assert (!$isunknown(wr));
      assert (!$isunknown(rd));
      assert (!$isunknown(din));
    end
 
 
 
    //////////////////// (7) Data must match
    
  property p1;
    integer waddr;
    logic [7:0] data;
 
    (wr, waddr = tb.i, data = din) |-> ##[1:30] rd ##0 (waddr == tb.i - 1, $display("din: %0d dout :%0d",data, dout));
  endproperty
  
  assert property (@(posedge clk) disable iff(rst) p1) $info("Suc at %0t",$time);
 
endmodule
 
 
//////////////////////////////////////////////////////////////////////////////////////////////
 
 
 
module tb;
  reg clk = 0, rst = 0, wr = 0, rd = 0;
  reg [7:0] din = 0;
  wire [7:0] dout;
  wire empty, full;
  integer i = 0;
  reg start = 0;
  
  initial begin
    #2;
    start = 1;
    #10;
    start = 0;
  end
  
  
  reg temp = 0;
  initial begin
    #292;
    temp = 1;
    #10;
    temp = 0;
  end
  
  FIFO dut (clk,rst,wr,rd,din,dout,empty,full);
  bind FIFO assert_fifo dut2 (clk,rst,wr,rd,din,dout,empty,full);
  
  
  
  always #5 clk = ~clk;
  
  
    task write();
    for( i = 0; i < 15; i++)
      begin   
        
        din = $urandom();
        wr = 1'b1;
        rd = 1'b0;
        @(posedge clk);
      end
  endtask
  
  
      task read();
    for( i = 0; i < 15; i++)
      begin   
        
        wr = 1'b0;
        rd = 1'b1;
        @(posedge clk);
      end
  endtask
  
  
  initial begin
    @(posedge clk) {rst,wr,rd} = 3'b100;
    @(posedge clk) {rst,wr,rd} = 3'b101;
    @(posedge clk) {rst,wr,rd} = 3'b110;
    @(posedge clk) {rst,wr,rd} = 3'b111;
    @(posedge clk) {rst,wr,rd} = 3'b000; 
    
    write();
    @(posedge clk) {rst,wr,rd} = 3'b010;
    @(posedge clk);
    
    read();
    
  end
  
  
  /*
  initial begin
 
    $display("------------Starting Test-----------------");
    $display("------(1) Behavior of FULL and EMPTY on RST High------");
    @(posedge clk) {rst,wr,rd} = 3'b100;
    @(posedge clk) {rst,wr,rd} = 3'b101;
    @(posedge clk) {rst,wr,rd} = 3'b110;
    @(posedge clk) {rst,wr,rd} = 3'b111;
    @(posedge clk) {rst,wr,rd} = 3'b000;
    @(posedge clk);
    #20;
 
    $display("------(2) Reading from Empty FIFO------");
    @(posedge clk) {rst,wr,rd} = 3'b001;
    @(posedge clk);
    
    #20;
    $display("------(3) Writing Data to FULL FIFO------");
    $display("--------(4) RPTR and WPTR behavior during Writing--------");
    write();
    @(posedge clk) {rst,wr,rd} = 3'b010;
    @(posedge clk);
    
    #20;
    $display("--------(5) RPTR and WPTR behavior during reading--------");
    read();
    
        
    
  end
  */
 
  
  //// ---------------- (6) Data Matched during read and write operation
  /*
  initial begin
    write();
    repeat(5) @(posedge clk);
    read(); 
  end
  
 */ 
     
   
  
  
  initial begin
    $dumpfile("dump.vcd");
    $dumpvars;
    $assertvacuousoff(0);
    #500;
    $finish();
  end
  
endmodule

SVAssertions_FIFO/dump.vcd
$date
Thu Jan 18 12:15:38 2024
$end
$version
Riviera-PRO Version 2022.04.117.8517
$end
$timescale
1 ns
$end

$scope module tb $end
$var wire 8 ! dout [7:0] $end
$var wire 1 " empty $end
$var wire 1 # full $end
$var reg 1 $ clk $end
$var reg 1 % rst $end
$var reg 1 & wr $end
$var reg 1 ' rd $end
$var reg 8 ( din [7:0] $end
$var integer 32 ) i $end
$var reg 1 * start $end
$var reg 1 + temp $end

$scope module dut $end
$var wire 1 , clk $end
$var wire 1 - rst $end
$var wire 1 . wr $end
$var wire 1 / rd $end
$var wire 8 0 din [7:0] $end
$var reg 8 1 dout [7:0] $end
$var reg 1 2 empty $end
$var reg 1 3 full $end
$var reg 4 4 wptr [3:0] $end
$var reg 4 5 rptr [3:0] $end
$var reg 4 6 cnt [3:0] $end

$scope module dut2 $end
$var wire 1 , clk $end
$var wire 1 - rst $end
$var wire 1 . wr $end
$var wire 1 / rd $end
$var wire 8 0 din [7:0] $end
$var wire 8 ! dout [7:0] $end
$var wire 1 " empty $end
$var wire 1 # full $end
$upscope $end

$upscope $end


$scope task write $end
$upscope $end


$scope task read $end
$upscope $end

$upscope $end

$enddefinitions $end
$dumpvars
bx !
1"
0#
0$
0%
0&
0'
b0 (
b0 )
0*
0+
0,
0-
0.
0/
b0 0
bx 1
12
03
b0 4
b0 5
b0 6
$end
#2
1*
#5
1$
1,
1%
1-
#10
0$
0,
#12
0*
#15
1$
1,
1'
1/
#20
0$
0,
#25
1$
1,
0'
1&
1.
0/
#30
0$
0,
#35
1$
1,
1'
1/
#40
0$
0,
#45
1$
1,
0'
1&
0%
b11001 (
b11001 0
0-
0/
#50
0$
0,
#55
1$
1,
b1 )
b10000 (
b10000 0
b1 4
b1 6
02
0"
#60
0$
0,
#65
1$
1,
b10 )
b10000000 (
b10000000 0
b10 4
b10 6
#70
0$
0,
#75
1$
1,
b11 )
b10110010 (
b10110010 0
b11 4
b11 6
#80
0$
0,
#85
1$
1,
b100 )
b110011 (
b110011 0
b100 4
b100 6
#90
0$
0,
#95
1$
1,
b101 )
b10110010 (
b10110010 0
b101 4
b101 6
#100
0$
0,
#105
1$
1,
b110 )
b101101 (
b101101 0
b110 4
b110 6
#110
0$
0,
#115
1$
1,
b111 )
b110011 (
b110011 0
b111 4
b111 6
#120
0$
0,
#125
1$
1,
b1000 )
b11001111 (
b11001111 0
b1000 4
b1000 6
#130
0$
0,
#135
1$
1,
b1001 )
b11100110 (
b11100110 0
b1001 4
b1001 6
#140
0$
0,
#145
1$
1,
b1010 )
b10000111 (
b10000111 0
b1010 4
b1010 6
#150
0$
0,
#155
1$
1,
b1011 )
b100111 (
b100111 0
b1011 4
b1011 6
#160
0$
0,
#165
1$
1,
b1100 )
b10111000 (
b10111000 0
b1100 4
b1100 6
#170
0$
0,
#175
1$
1,
b1101 )
b11101111 (
b11101111 0
b1101 4
b1101 6
#180
0$
0,
#185
1$
1,
b1110 )
b10101110 (
b10101110 0
b1110 4
b1110 6
#190
0$
0,
#195
1$
1,
b1111 )
b1111 4
b1111 6
13
1#
#200
0$
0,
#205
1$
1,
b0 4
#210
0$
0,
#215
1$
1,
b0 )
0&
1'
1/
0.
#220
0$
0,
#225
1$
1,
b1 )
b11001 1
b1 5
b1110 6
03
0#
b11001 !
#230
0$
0,
#235
1$
1,
b10 )
b10000 1
b10 5
b1101 6
b10000 !
#240
0$
0,
#245
1$
1,
b11 )
b10000000 1
b11 5
b1100 6
b10000000 !
#250
0$
0,
#255
1$
1,
b100 )
b10110010 1
b100 5
b1011 6
b10110010 !
#260
0$
0,
#265
1$
1,
b101 )
b110011 1
b101 5
b1010 6
b110011 !
#270
0$
0,
#275
1$
1,
b110 )
b10110010 1
b110 5
b1001 6
b10110010 !
#280
0$
0,
#285
1$
1,
b111 )
b101101 1
b111 5
b1000 6
b101101 !
#290
0$
0,
#292
1+
#295
1$
1,
b1000 )
b110011 1
b1000 5
b111 6
b110011 !
#300
0$
0,
#302
0+
#305
1$
1,
b1001 )
b11001111 1
b1001 5
b110 6
b11001111 !
#310
0$
0,
#315
1$
1,
b1010 )
b11100110 1
b1010 5
b101 6
b11100110 !
#320
0$
0,
#325
1$
1,
b1011 )
b10000111 1
b1011 5
b100 6
b10000111 !
#330
0$
0,
#335
1$
1,
b1100 )
b100111 1
b1100 5
b11 6
b100111 !
#340
0$
0,
#345
1$
1,
b1101 )
b10111000 1
b1101 5
b10 6
b10111000 !
#350
0$
0,
#355
1$
1,
b1110 )
b11101111 1
b1110 5
b1 6
b11101111 !
#360
0$
0,
#365
1$
1,
b1111 )
b10101110 1
b1111 5
b0 6
12
1"
b10101110 !
#370
0$
0,
#375
1$
1,
b0 5
